ksef_utils/__init__.py
ksef_utils/__main__.py
ksef_utils/cli.py
ksef_utils/config.py
ksef_utils/server.py
ksef_utils/utils.py
tests/__init__.py
tests/conftest.py
tests/test_e2e.py
tests/test_ksef.py
tests/test_selfinvoicing.py
ksef_utils-1.4.dist-info/LICENSE
ksef_utils-1.4.dist-info/METADATA
ksef_utils-1.4.dist-info/WHEEL
ksef_utils-1.4.dist-info/entry_points.txt
ksef_utils-1.4.dist-info/top_level.txt
ksef_utils-1.4.dist-info/RECORD
