Metadata-Version: 2.1
Name: ksef-utils
Version: 1.4
Summary: "KSeF Python client for creating invoices"
Home-page: https://github.com/pprzetacznik/ksef-utils
Author: Piotr Przetacznik
Author-email: "piotr.przetacznik+ksef@gmail.com",
Keywords: invoices,ksef
Classifier: Development Status :: 5 - Production/Stable
Classifier: Environment :: Console
Classifier: Intended Audience :: Developers
Classifier: Intended Audience :: System Administrators
Classifier: Intended Audience :: Financial and Insurance Industry
Classifier: Intended Audience :: End Users/Desktop
Classifier: Intended Audience :: Customer Service
Classifier: License :: Other/Proprietary License
Classifier: Programming Language :: Python :: 3.11
Classifier: Programming Language :: Python :: 3.12
License-File: LICENSE
Requires-Dist: requests
Requires-Dist: pytest
Requires-Dist: pytest-cov
Requires-Dist: pytest-bdd
Requires-Dist: Jinja2
Requires-Dist: pycryptodome
Requires-Dist: lxml
Requires-Dist: pytz
Requires-Dist: signxml==3.2.1
Requires-Dist: Sphinx
Requires-Dist: sphinx-rtd-theme
